{
  "updated": "2026-07-19T18:57:33.665578Z",
  "users": {
    "Sofi": "",
    "Shabnam": "",
    "prMarian": "",
    "Nozhan": "",
    "Katrina": "",
    "Taniya": "",
    "Farimah": "",
    "Zespina": "online",
    "Elsa": "",
    "Suzan": "",
    "Lara": "online",
    "Sahar": "",
    "Juju": "",
    "aY5A": "",
    "Mobina": "",
    "Parisa": "",
    "Blueberry": "online",
    "Hooriya": "",
    "Naz ahwaz": "online",
    "Sahel": "",
    "Mira": "",
    "Maral": "",
    "Roya": "online",
    "Sernay": "",
    "Elnaz": "online",
    "Sadaf": "",
    "Elham": "",
    "oos Shaboon": ""
  }
}