{
  "updated": "2026-07-08T19:25:30.138090Z",
  "users": {
    "Sofi": "online",
    "Shabnam": ".",
    "prMarian": "online",
    "Katrina": ".",
    "Taniya": ".",
    "Farimah": ".",
    "Zespina": ".",
    "Elsa": ".",
    "Suzan": ".",
    "Lara": ".",
    "Sahar": ".",
    "Farimah juju": ".",
    "Parisa": "online",
    "Blueberry": ".",
    "Hooriya": ".",
    "Naz ahwaz": "online",
    "Sahel": ".",
    "Mira": ".",
    "Maral": "online",
    "Roya": "online",
    "Nozhan": ".",
    "Sernay": ".",
    "Elnaz": "online",
    "Sadaf": ".",
    "oos Shaboon": "."
  }
}